ed25519ll-0.4.dist-info/RECORD
ed25519ll-0.4.dist-info/WHEEL
ed25519ll-0.4.dist-info/METADATA
ed25519ll/_ed25519_linux_x86_64.so
ed25519ll/test.py
ed25519ll/_ed25519.py
ed25519ll/__init__.py
