Metadata-Version: 1.2
Name: ed25519ll
Version: 0.4
Summary: A low-level cffi wrapper for Ed25519 digital signatures.
Home-page: http://bitbucket.org/dholth/ed25519ll/
Author: Daniel Holth
Author-email: dholth@fastmail.fm
License: MIT
Keywords: ed25519
Platform: UNKNOWN
Classifier: Development Status :: 4 - Beta
Classifier: Intended Audience :: Developers
Classifier: Programming Language :: Python
Classifier: Topic :: Security :: Cryptography
Requires-Dist: cffi
